LICENSE
seo_cap/__init__.py
seo_cap-0.1.0.dist-info/LICENSE
seo_cap-0.1.0.dist-info/WHEEL
seo_cap-0.1.0.dist-info/METADATA
seo_cap-0.1.0.dist-info/RECORD
