Metadata-Version: 2.1
Name: seo-cap
Version: 0.1.0
Summary: Utils for websites regarding SEO
Home-page: https://github.com/mintyPT/seo-cap
License: MIT
Keywords: seo
Author: mg santos
Author-email: mauro.goncalo@gmail.com
Requires-Python: >=3.6,<4.0
Classifier: License :: OSI Approved :: MIT License
Classifier: Programming Language :: Python :: 3
Classifier: Programming Language :: Python :: 3.6
Classifier: Programming Language :: Python :: 3.7
Classifier: Programming Language :: Python :: 3.8
Classifier: Programming Language :: Python :: 3.9
Project-URL: Repository, https://github.com/mintyPT/seo-cap
